[
  {
    "id": "sermon-2025-03-23",
    "title": "Credința care mișcă munții",
    "speaker": "Pastor Ioan Popa",
    "date": "2025-03-23",
    "description": "Un mesaj despre puterea credinței autentice și cum transformă ea viața noastră zilnică.",
    "youtubeVideoId": "dQw4w9WgXcQ",
    "series": "Credința vie",
    "tags": ["credință", "rugăciune"]
  },
  {
    "id": "sermon-2025-03-16",
    "title": "Harul lui Dumnezeu este suficient",
    "speaker": "Pastor Ioan Popa",
    "date": "2025-03-16",
    "description": "Explorăm promisiunea din 2 Corinteni 12:9 — harul Lui ne ajunge în orice circumstanță.",
    "youtubeVideoId": "dQw4w9WgXcQ",
    "series": null,
    "tags": ["har", "putere"]
  },
  {
    "id": "sermon-2025-03-09",
    "title": "Pacea care întrece orice pricepere",
    "speaker": "Pastor Ioan Popa",
    "date": "2025-03-09",
    "description": "Filipeni 4:7 — ce înseamnă să trăiești în pacea lui Dumnezeu chiar și în mijlocul furtunii.",
    "youtubeVideoId": "dQw4w9WgXcQ",
    "series": null,
    "tags": ["pace", "Filipeni"]
  },
  {
    "id": "sermon-2025-02-23",
    "title": "Iubire neclintită",
    "speaker": "Pastor Ioan Popa",
    "date": "2025-02-23",
    "description": "Romani 8:38-39 — nimic nu ne poate despărți de dragostea lui Dumnezeu.",
    "youtubeVideoId": "dQw4w9WgXcQ",
    "series": null,
    "tags": ["iubire", "Romani"]
  },
  {
    "id": "sermon-2025-02-16",
    "title": "Chemarea lui Dumnezeu",
    "speaker": "Pastor Ioan Popa",
    "date": "2025-02-16",
    "description": "Cum discernem chemarea lui Dumnezeu pentru viața noastră și cum răspundem cu încredere.",
    "youtubeVideoId": "dQw4w9WgXcQ",
    "series": "Chemați și aleși",
    "tags": ["chemare", "misiune"]
  },
  {
    "id": "sermon-2025-02-09",
    "title": "Rugăciunea neîncetată",
    "speaker": "Pastor Ioan Popa",
    "date": "2025-02-09",
    "description": "1 Tesaloniceni 5:17 — ce înseamnă practic să te rogi fără încetare.",
    "youtubeVideoId": "dQw4w9WgXcQ",
    "series": null,
    "tags": ["rugăciune"]
  }
]
